<?xml version="1.0" encoding="utf-8"?>
<Civ4GameText xmlns="http://www.firaxis.com">
	<TEXT>
		<Tag>TXT_KEY_EMPHASIZE_COAL</Tag>
		<English>Emphasize Coal</English>
		<German>Schwerpunkt Kohle</German>
	</TEXT>
	<TEXT>
		<Tag>TXT_KEY_EMPHASIZE_NO_COAL</Tag>
		<English>Deemphasize Coal</English>
		<German>Schwerpunkt Kohle aufheben</German>
	</TEXT>
	<TEXT>
		<Tag>TXT_KEY_EMPHASIZE_BLACK_POWDER</Tag>
		<English>Emphasize Gunpowder</English>
		<German>Schwerpunkt Schwarzpulver</German>
	</TEXT>
	<TEXT>
		<Tag>TXT_KEY_EMPHASIZE_NO_BLACK_POWDER</Tag>
		<English>Deemphasize Gunpowder</English>
		<German>Schwerpunkt Schwarzpulver aufheben</German>
	</TEXT>
	<TEXT>
		<Tag>TXT_KEY_EMPHASIZE_BAKERY_GOODS</Tag>
		<English>Emphasize Bakery Goods</English>
		<German>Schwerpunkt Proviant</German>
	</TEXT>
	<TEXT>
		<Tag>TXT_KEY_EMPHASIZE_NO_BAKERY_GOODS</Tag>
		<English>Deemphasize Bakery Goods</English>
		<German>Schwerpunkt Proviant aufheben</German>
	</TEXT>
	<TEXT>
		<Tag>TXT_KEY_EMPHASIZE_CHICKEN</Tag>
		<English>Emphasize Chicken</English>
		<German>Schwerpunkt Hühner</German>
	</TEXT>
	<TEXT>
		<Tag>TXT_KEY_EMPHASIZE_NO_CHICKEN</Tag>
		<English>Deemphasize Chicken</English>
		<German>Schwerpunkt Hühner aufheben</German>
	</TEXT>
	<TEXT>
		<Tag>TXT_KEY_EMPHASIZE_DOWNS</Tag>
		<English>Emphasize Down</English>
		<German>Schwerpunkt Daunen</German>
	</TEXT>
	<TEXT>
		<Tag>TXT_KEY_EMPHASIZE_NO_DOWNS</Tag>
		<English>Deemphasize Down</English>
		<German>Schwerpunkt Daunen aufheben</German>
	</TEXT>
	<TEXT>
		<Tag>TXT_KEY_EMPHASIZE_OLIVES</Tag>
		<English>Emphasize Olives</English>
		<German>Schwerpunkt Oliven</German>
	</TEXT>
	<TEXT>
		<Tag>TXT_KEY_EMPHASIZE_NO_OLIVES</Tag>
		<English>Deemphasize Olives</English>
		<German>Schwerpunkt Oliven aufheben</German>
	</TEXT>
	<TEXT>
		<Tag>TXT_KEY_EMPHASIZE_MAPLE_SIRUP</Tag>
		<English>Emphasize Maple Syrup</English>
		<German>Schwerpunkt Ahornsirup</German>
	</TEXT>
	<TEXT>
		<Tag>TXT_KEY_EMPHASIZE_NO_MAPLE_SIRUP</Tag>
		<English>Deemphasize Maple Syrup</English>
		<German>Schwerpunkt Ahornsirup aufheben</German>
	</TEXT>
	<TEXT>
		<Tag>TXT_KEY_EMPHASIZE_FESTIVE_CLOTHES</Tag>
		<English>Emphasize Festive Clothes</English>
		<German>Schwerpunkt Festliche Kleidung</German>
	</TEXT>
	<TEXT>
		<Tag>TXT_KEY_EMPHASIZE_NO_FESTIVE_CLOTHES</Tag>
		<English>Deemphasize Festive Clothes</English>
		<German>Schwerpunkt Festliche Kleidung aufheben</German>
	</TEXT>
	<TEXT>
		<Tag>TXT_KEY_EMPHASIZE_EVERYDAY_CLOTHES</Tag>
		<English>Emphasize Everyday Clothes</English>
		<German>Schwerpunkt Alltagskleidung</German>
	</TEXT>
	<TEXT>
		<Tag>TXT_KEY_EMPHASIZE_NO_EVERYDAY_CLOTHES</Tag>
		<English>Deemphasize Everyday Clothes</English>
		<German>Schwerpunkt Alltagskleidung aufheben</German>
	</TEXT>
	<TEXT>
		<Tag>TXT_KEY_EMPHASIZE_CHEESE</Tag>
		<English>Emphasize Cheese</English>
		<German>Schwerpunkt Käse</German>
	</TEXT>
	<TEXT>
		<Tag>TXT_KEY_EMPHASIZE_NO_CHEESE</Tag>
		<English>Deemphasize Cheese</English>
		<German>Schwerpunkt Käse aufheben</German>
	</TEXT>
	<TEXT>
		<Tag>TXT_KEY_EMPHASIZE_COLOURED_WOOL_CLOTH</Tag>
		<English>Emphasize Coloured Wool Cloth</English>
		<German>Schwerpunkt Gefärbter Wollstoff</German>
	</TEXT>
	<TEXT>
		<Tag>TXT_KEY_EMPHASIZE_NO_COLOURED_WOOL_CLOTH</Tag>
		<English>Deemphasize Coloured Wool Cloth</English>
		<German>Schwerpunkt Gefärbter Wollstoff aufheben</German>
	</TEXT>
	<TEXT>
		<Tag>TXT_KEY_EMPHASIZE_PADDED_LEATHER_COATS</Tag>
		<English>Emphasize Lined Leather Coats</English>
		<German>Schwerpunkt Gefütterte Ledermäntel</German>
	</TEXT>
	<TEXT>
		<Tag>TXT_KEY_EMPHASIZE_NO_PADDED_LEATHER_COATS</Tag>
		<English>Deemphasize Lined Leather Coats</English>
		<German>Schwerpunkt Gefütterte Ledermäntel aufheben</German>
	</TEXT>
	<TEXT>
		<Tag>TXT_KEY_EMPHASIZE_OLIVE_OIL</Tag>
		<English>Emphasize Olive Oil</English>
		<German>Schwerpunkt Olivenöl</German>
	</TEXT>
	<TEXT>
		<Tag>TXT_KEY_EMPHASIZE_NO_OLIVE_OIL</Tag>
		<English>Deemphasize Olive Oil</English>
		<German>Schwerpunkt Olivenöl aufheben</German>
	</TEXT>
	<TEXT>
		<Tag>TXT_KEY_EMPHASIZE_PADDED_FURNITURE</Tag>
		<English>Emphasize Upholstered Furniture</English>
		<German>Schwerpunkt Polstermöbel</German>
	</TEXT>
	<TEXT>
		<Tag>TXT_KEY_EMPHASIZE_NO_PADDED_FURNITURE</Tag>
		<English>Deemphasize Upholstered Furniture</English>
		<German>Schwerpunkt Polstermöbel aufheben</German>
	</TEXT>
	<TEXT>
		<Tag>TXT_KEY_EMPHASIZE_FIELD_WORKER_TOOLS</Tag>
		<English>Emphasize Fieldworker Tools</English>
		<German>Schwerpunkt Feldarbeiterwerkzeuge</German>
	</TEXT>
	<TEXT>
		<Tag>TXT_KEY_EMPHASIZE_NO_FIELD_WORKER_TOOLS</Tag>
		<English>Deemphasize Fieldworker Tools</English>
		<German>Schwerpunkt Feldarbeiterwerkzeuge aufheben</German>
	</TEXT>
	<TEXT>
		<Tag>TXT_KEY_EMPHASIZE_HOUSEHOLD_GOODS</Tag>
		<English>Emphasize Household Goods</English>
		<German>Schwerpunkt Haushaltswaren</German>
	</TEXT>
	<TEXT>
		<Tag>TXT_KEY_EMPHASIZE_NO_HOUSEHOLD_GOODS</Tag>
		<English>Deemphasize Household Goods</English>
		<German>Schwerpunkt Haushaltswaren aufheben</German>
	</TEXT>
	<TEXT>
		<Tag>TXT_KEY_EMPHASIZE_CULTURE</Tag>
		<English>Emphasize Culture</English>
		<German>Schwerpunkt Kultur</German>
	</TEXT>
	<TEXT>
		<Tag>TXT_KEY_EMPHASIZE_NO_CULTURE</Tag>
		<English>Deemphasize Culture</English>
		<German>Schwerpunkt Kultur aufheben</German>
	</TEXT>
	<TEXT>
		<Tag>TXT_KEY_EMPHASIZE_HEALTH</Tag>
		<English>Emphasize Health</English>
		<German>Schwerpunkt Gesundheit</German>
	</TEXT>
	<TEXT>
		<Tag>TXT_KEY_EMPHASIZE_NO_HEALTH</Tag>
		<English>Deemphasize Health</English>
		<German>Schwerpunkt Gesundheit aufheben</German>
	</TEXT>
</Civ4GameText>
